Workbook

Sheet Portfolio_Model
A1: WHARTON GLOBAL YOUTH INVESTMENT COMPETITION: DYNAMIC PORTFOLIO MODEL
A2: Client: Laura Gao | Creative Residency in Taiwan | Automated Formula-Driven Compounding Engine
A4: MODEL ASSUMPTIONS & PARAMETERS | E4: MARKET CAP RETURN BENCHMARKS
A5: Parameter Name | B5: Value | C5: Notes / Logic | E5: Market Cap Category | F5: Annual Return Assumption | G5: Description / Risk Profile
A6: Initial Investment (2027 / Year 1) | B6: 300000 | C6: Total Year 1 cash deployment | E6: Large Cap | F6: 0.12 | G6: Established global leaders (> $10B cap); defensive compounding
A7: Follow-on Contribution (2028 / Year 2) | B7: 150000 | C7: Total Year 2 cash deployment | E7: Mid Cap | F7: 0.15 | G7: High-growth secular compounders ($2B - $10B cap); margin expansion
A8: Total Principal Capital Invested | B8: =B5+B6 | C8: Formula: Sum of contributions | E8: Small Cap | F8: 0.18 | G8: High-beta emerging leaders (< $2B cap); elevated capital growth
A9: Mandatory Operating Reserve in 2033 | B9: 420000 | C9: Guarantees 10 x $50k annual payments | E9: Cash / Liquidity Buffer | F9: 0.0425 | G9: Short-term US Treasury bills / money market dry powder
A10: Operating Payment Annuity (2033-2042) | B10: 50000 | C10: Fixed annual payment to residency
A11: Target Residency Launch Year | B11: 2033 | C11: Year 7 of competition timeline
A13: RECOMMENDED ASSET ALLOCATION & RETURN ENGINE
A15: KO | B15: The Coca-Cola Co | C15: Consumer Staples | D15: Large Cap | E15: 0.25 | F15: =VLOOKUP(D15, $E$6:$F$9, 2, FALSE) | G15: =E15 * $B$6 | H15: =E15 * $B$7 | I15: =G15 + H15 | J15: =E15 * F15 | K15: Recession-proof cash flow & 62-year dividend growth
A16: CL | B16: Colgate-Palmolive | C16: Consumer Staples | D16: Large Cap | E16: 0.25 | F16: =VLOOKUP(D16, $E$6:$F$9, 2, FALSE) | G16: =E16 * $B$6 | H16: =E16 * $B$7 | I16: =G16 + H16 | J16: =E16 * F16 | K16: 61.8% Golden Pocket ($85.32); ultra-low beta (~0.50)
A17: V | B17: Visa Inc | C17: Financials / Payments | D17: Large Cap | E17: 0.15 | F17: =VLOOKUP(D17, $E$6:$F$9, 2, FALSE) | G17: =E17 * $B$6 | H17: =E17 * $B$7 | I17: =G17 + H17 | J17: =E17 * F17 | K17: Secular electronic payments duopoly; >50% operating margins
A18: UNH | B18: UnitedHealth Group | C18: Healthcare | D18: Large Cap | E18: 0.1 | F18: =VLOOKUP(D18, $E$6:$F$9, 2, FALSE) | G18: =E18 * $B$6 | H18: =E18 * $B$7 | I18: =G18 + H18 | J18: =E18 * F18 | K18: Healthcare compounding; Optum high-margin cash engine
A19: HD | B19: Home Depot Inc | C19: Consumer Discretionary | D19: Large Cap | E19: 0.1 | F19: =VLOOKUP(D19, $E$6:$F$9, 2, FALSE) | G19: =E19 * $B$6 | H19: =E19 * $B$7 | I19: =G19 + H19 | J19: =E19 * F19 | K19: High ROIC (>35%) consumer home improvement monopoly
A20: RKT | B20: Reckitt Benckiser | C20: Consumer Staples | D20: Large Cap | E20: 0.1 | F20: =VLOOKUP(D20, $E$6:$F$9, 2, FALSE) | G20: =E20 * $B$6 | H20: =E20 * $B$7 | I20: =G20 + H20 | J20: =E20 * F20 | K20: 4.2% dividend yield + litigation recovery turnaround alpha
A21: CASH | B21: Short-Term Cash Buffer | C21: Cash & Treasuries | D21: Cash / Liquidity Buffer | E21: 0.05 | F21: =VLOOKUP(D21, $E$6:$F$9, 2, FALSE) | G21: =E21 * $B$6 | H21: =E21 * $B$7 | I21: =G21 + H21 | J21: =E21 * F21 | K21: Dry powder for opportunistic limit orders & rebalancing
A22: TOTAL | E22: =SUM(E15:E21) | F22: BLENDED CAGR: | G22: =SUM(G15:G21) | H22: =SUM(H15:H21) | I22: =SUM(I15:I21) | J22: =SUM(J15:J21) | K22: =IF(ROUND(E22,2)=1, '100% Balanced', 'ALERT: Weight must equal 100%')
A25: YEAR-BY-YEAR FINANCIAL PROJECTION MODEL (2026–2033)
A27: Year 0 | B27: 2026 | C27: 0 | D27: =0 | E27: =$J$22 | F27: =(C27 + D27) * E27 | G27: =C27 + D27 + F27 | H27: Baseline year; set up target entry limit orders
A28: Year 1 | B28: 2027 | C28: =G27 | D28: =$B$6 | E28: =$J$22 | F28: =(C28 + D28) * E28 | G28: =C28 + D28 + F28 | H28: Deploy Tranche 1 across KO, CL, V, UNH, HD, RKT
A29: Year 2 | B29: 2028 | C29: =G28 | D29: =$B$7 | E29: =$J$22 | F29: =(C29 + D29) * E29 | G29: =C29 + D29 + F29 | H29: Deploy Tranche 2; full $450k capital actively compounding
A30: Year 3 | B30: 2029 | C30: =G29 | D30: =0 | E30: =$J$22 | F30: =(C30 + D30) * E30 | G30: =C30 + D30 + F30 | H30: Compounding phase; all dividends automatically reinvested (DRIP)
A31: Year 4 | B31: 2030 | C31: =G30 | D31: =0 | E31: =$J$22 | F31: =(C31 + D31) * E31 | G31: =C31 + D31 + F31 | H31: Portfolio crosses $600k mark
A32: Year 5 | B32: 2031 | C32: =G31 | D32: =0 | E32: =$J$22 | F32: =(C32 + D32) * E32 | G32: =C32 + D32 + F32 | H32: Approach Co-Sponsors: Pledge $260k–$340k facility contribution
A33: Year 6 | B33: 2032 | C33: =G32 | D33: =0 | E33: =$J$22 | F33: =(C33 + D33) * E33 | G33: =C33 + D33 + F33 | H33: Begin de-risking cash flows into 10-year Treasury bond ladder
A34: Year 7 | B34: 2033 | C34: =G33 | D34: =0 | E34: =$J$22 | F34: =(C34 + D34) * E34 | G34: =C34 + D34 + F34 | H34: Residency Launch: Lock Operating Reserve & Disburse Facility
A37: 2033 RESIDENCY GOAL EXECUTION & DISBURSAL (AUTOMATED FORMULA CHECK)
A38: Metric / Objective | B38: Formula / Amount ($) | C38: Status / Compliance | D38: Impact on Laura Gao's Mandate
A39: Total Portfolio Value at Launch (2033) | B39: =G34 | C39: Formula: 2033 Ending Balance | D39: Portfolio reaches target size
A40: Mandatory Operating Reserve Set-Aside | B40: =$B$9 | C40: Formula: Target Operating Reserve | D40: Fully segregated into bond ladder
A41: 10-Year Operating Commitment Check | B41: =IF(B40>=$B$9, '100% FUNDED & GUARANTEED', 'DEFICIT') | C41: High Certainty Test | D41: 10 payments of $50,000 (2033-2042) guaranteed
A42: Remaining Capital for Facility Contribution | B42: =B39-B40 | C42: Formula: Total Portfolio - Operating Reserve | D42: Direct personal equity into Taiwan facility
A43: Facility Contribution Target Status | B43: =IF(B42>=225000, 'EXCEEDS TARGET ($225k-$325k)', 'BELOW TARGET') | C43: Co-Sponsor Target Alignment | D43: Signals financial viability to sponsors in 2031

Sheet Approved_Stocks_Database
A1: SHORTLISTED APPROVED STOCKS DATABASE (PRICE > $5.50 USD ONLY)
A2: Dynamic formula-based returns by market cap: Large Cap = 12%, Mid Cap = 15%, Small Cap = 18%
A5: 1 | B5: KO | C5: The Coca-Cola Co | D5: Consumer Staples | E5: 85.7 | F5: Large Cap | G5: =VLOOKUP(F5, Portfolio_Model!$E$6:$F$9, 2, FALSE) | H5: Resting at 1Y VWAP ($86.50); tight 50/200 EMA coil; above 23.6% Fib. | I5: Unrivaled global distribution; pricing power; 62-year Dividend King. 10Y CAGR: 10.7%. | J5: $82.80 – $85.50 | K5: Core Anchor (25%)
A6: 2 | B6: CL | C6: Colgate-Palmolive | D6: Consumer Staples | E6: 84.26 | F6: Large Cap | G6: =VLOOKUP(F6, Portfolio_Model!$E$6:$F$9, 2, FALSE) | H6: At 61.8% Golden Pocket ($85.32); 5.3% discount to 1Y VWAP ($89). | I6: >40% global oral care share + Hill's Pet Nutrition; 61-yr Dividend King. Beta ~0.50. | J6: $83.50 – $85.50 | K6: Core Anchor (25%)
A7: 3 | B7: V | C7: Visa Inc | D7: Financials / Payments | E7: 272 | F7: Large Cap | G7: =VLOOKUP(F7, Portfolio_Model!$E$6:$F$9, 2, FALSE) | H7: Holding 50 EMA ($275) & 200 EMA ($268); tight consolidation near ATH. | I7: Worldwide payments duopoly (>50% operating margins); natural inflation beneficiary. | J7: $268 – $276 | K7: Core Anchor (15%)
A8: 4 | B8: UNH | C8: UnitedHealth Group | D8: Healthcare | E8: 565 | F8: Large Cap | G8: =VLOOKUP(F8, Portfolio_Model!$E$6:$F$9, 2, FALSE) | H8: Rebounding off 200 EMA ($560); resting at 1Y VWAP ($540); secular bull. | I8: Dominant healthcare insurer + Optum health-services juggernaut; 15-yr dividend hikes. | J8: $550 – $575 | K8: Core Anchor (10%)
A9: 5 | B9: HD | C9: Home Depot Inc | D9: Consumer Discretionary | E9: 375 | F9: Large Cap | G9: =VLOOKUP(F9, Portfolio_Model!$E$6:$F$9, 2, FALSE) | H9: Above 50/200 EMA; bouncing off 1Y VWAP ($375); steady upward trend. | I9: Dominant home improvement duopoly; high ROIC (>35%); strong dividend growth. | J9: $365 – $380 | K9: Core Anchor (10%)
A10: 6 | B10: RKT | C10: Reckitt Benckiser | D10: Consumer Staples | E10: 64.5 | F10: Large Cap | G10: =VLOOKUP(F10, Portfolio_Model!$E$6:$F$9, 2, FALSE) | H10: Reclaiming 200 EMA & 1Y VWAP (~4,850 GBX); double bottom off 78.6% Fib. | I10: Essential health/hygiene (Dettol, Lysol); 4.2% yield; turnaround catalyst. | J10: 4,700 – 4,880 GBX | K10: Core Anchor (10%)
A11: 7 | B11: ASML | C11: ASML Holding NV | D11: Technology / Chips | E11: 795 | F11: Large Cap | G11: =VLOOKUP(F11, Portfolio_Model!$E$6:$F$9, 2, FALSE) | H11: Pullback to 61.8% Fib ($780–$820); below 50 EMA, testing 200 EMA. | I11: Absolute global monopoly in EUV lithography; mission-critical to all AI & semis. | J11: $750 – $810 | K11: Satellite Growth
A12: 8 | B12: AVGO | C12: Broadcom Inc | D12: Technology / Chips | E12: 152 | F12: Large Cap | G12: =VLOOKUP(F12, Portfolio_Model!$E$6:$F$9, 2, FALSE) | H12: Bullish trend; consolidating above 50/200 EMA and 1Y VWAP ($145). | I12: Premier custom AI silicon (XPU), VMware cash cow, 15-yr dividend growth. | J12: $145 – $155 | K12: Satellite Growth
A13: 9 | B13: SAP | C13: SAP SE | D13: Technology / Software | E13: 210 | F13: Large Cap | G13: =VLOOKUP(F13, Portfolio_Model!$E$6:$F$9, 2, FALSE) | H13: Strong momentum; consolidating above 50/200 EMA; cloud backlog expanding. | I13: Mission-critical enterprise ERP software; extremely high client switching costs. | J13: €185 – €195 | K13: Satellite Growth
A14: 10 | B14: TCS | C14: Tata Consultancy Services | D14: Technology / IT | E14: 49.5 | F14: Large Cap | G14: =VLOOKUP(F14, Portfolio_Model!$E$6:$F$9, 2, FALSE) | H14: Near 200 EMA (~₹4,150); above 1Y VWAP; rock-solid cash generative base. | I14: Global IT consulting titan; >25% operating margins; zero debt; 70%+ payout ratio. | J14: ₹4,050 – ₹4,200 | K14: Satellite Quality
A15: 11 | B15: RY | C15: Royal Bank of Canada | D15: Financials | E15: 114 | F15: Large Cap | G15: =VLOOKUP(F15, Portfolio_Model!$E$6:$F$9, 2, FALSE) | H15: In secular uptrend above 50/200 EMA; premier tier 1 capital ratio. | I15: Canada's #1 financial institution; dominant wealth & retail moat; 3.8% yield. | J15: C$150 – C$156 | K15: Satellite Quality
A16: 12 | B16: ASIANPAINT | C16: Asian Paints Ltd | D16: Materials / Coatings | E16: 36.4 | F16: Large Cap | G16: =VLOOKUP(F16, Portfolio_Model!$E$6:$F$9, 2, FALSE) | H16: Consolidating near 200 EMA; testing 61.8% Fib support (~₹2,950–₹3,100). | I16: Dominant Indian decorative coatings monopoly; pricing power; high ROE. | J16: ₹2,950 – ₹3,150 | K16: Satellite Quality
... A24: 20 | B24: M&M | C24: Mahindra & Mahindra | D24: Consumer Discretionary | E24: 33.5 | F24: Large Cap | G24: =VLOOKUP(F24, Portfolio_Model!$E$6:$F$9, 2, FALSE) | H24: Strong uptrend above 50/200 EMA; India rural/tractor & SUV powerhouse. | I24: Thriving in Indian automotive and farm machinery; high capital efficiency. | J24: ₹2,700 – ₹2,850 | K24: Satellite Growth
